windows_entry_exe/__init__.py
windows_entry_exe/t32.exe
windows_entry_exe/t64.exe
windows_entry_exe/w32.exe
windows_entry_exe/w64.exe
windows_entry_exe-1.3.dist-info/LICENSE
windows_entry_exe-1.3.dist-info/METADATA
windows_entry_exe-1.3.dist-info/WHEEL
windows_entry_exe-1.3.dist-info/entry_points.txt
windows_entry_exe-1.3.dist-info/top_level.txt
windows_entry_exe-1.3.dist-info/zip-safe
windows_entry_exe-1.3.dist-info/RECORD
