Metadata-Version: 2.1
Name: windows_entry_exe
Version: 1.3
Summary: Replacement exe launchers for setuptools entry_points
Home-page: https://gitlab.com/alelec/windows-entry-exe/
Author: Andrew Leech
Author-email: andrew@alelec.net
License: MIT
Requires-Python: >=3.2
License-File: LICENSE
